{
    "rhino-core": {
        "branch": "dev",
        "description": "Instructions to deploy the required services for DeversiFi Exchange",
        "homepage": "",
        "owner": "rhinofi",
        "repo": "rhino-core",
        "rev": "7f13125bb38f0fdd615416c18f984f00b1596773",
        "sha256": "03hq5xhlig207rhx2kqk7vddiyagcy1idaqvv6qi6a2c1xnziyq2",
        "type": "tarball",
        "url": "https://github.com/rhinofi/rhino-core/archive/7f13125bb38f0fdd615416c18f984f00b1596773.tar.gz",
        "url_template": "https://github.com/<owner>/<repo>/archive/<rev>.tar.gz"
    }
}
